oascmd.py
setup.cfg
setup.py
oas/__init__.py
oas/oas_api.py
oas/oas_ops.py
oas/oas_util.py
oas/ease/__init__.py
oas/ease/api.py
oas/ease/exceptions.py
oas/ease/job.py
oas/ease/merkle.py
oas/ease/response.py
oas/ease/uploader.py
oas/ease/utils.py
oas/ease/vault.py
oassdk.egg-info/PKG-INFO
oassdk.egg-info/SOURCES.txt
oassdk.egg-info/dependency_links.txt
oassdk.egg-info/requires.txt
oassdk.egg-info/top_level.txt