Metadata-Version: 1.0
Name: oassdk
Version: 0.2.5
Summary: Python SDK for Aliyun OAS (Open Archive Service)
Home-page: http://www.aliyun.com/product/oas
Author: Aliyun OAS
Author-email: jianyi.weng@alibaba-inc.com
License: GPL version 2
Platform: UNKNOWN
